odoo/addons/account_cash_invoice/README.rst
odoo/addons/account_cash_invoice/__init__.py
odoo/addons/account_cash_invoice/__manifest__.py
odoo/addons/account_cash_invoice/i18n/account_cash_invoice.pot
odoo/addons/account_cash_invoice/i18n/es_PA.po
odoo/addons/account_cash_invoice/i18n/hr.po
odoo/addons/account_cash_invoice/i18n/pt.po
odoo/addons/account_cash_invoice/models/__init__.py
odoo/addons/account_cash_invoice/models/account_bank_statement.py
odoo/addons/account_cash_invoice/models/account_bank_statement_line.py
odoo/addons/account_cash_invoice/readme/CONTRIBUTORS.rst
odoo/addons/account_cash_invoice/readme/DESCRIPTION.rst
odoo/addons/account_cash_invoice/readme/ROADMAP.rst
odoo/addons/account_cash_invoice/readme/USAGE.rst
odoo/addons/account_cash_invoice/security/ir.model.access.csv
odoo/addons/account_cash_invoice/static/description/icon.png
odoo/addons/account_cash_invoice/static/description/index.html
odoo/addons/account_cash_invoice/tests/__init__.py
odoo/addons/account_cash_invoice/tests/test_pay_invoice.py
odoo/addons/account_cash_invoice/wizard/__init__.py
odoo/addons/account_cash_invoice/wizard/cash_invoice_in.py
odoo/addons/account_cash_invoice/wizard/cash_invoice_in.xml
odoo/addons/account_cash_invoice/wizard/cash_invoice_out.py
odoo/addons/account_cash_invoice/wizard/cash_invoice_out.xml
odoo14_addon_account_cash_invoice-14.0.1.3.0.dist-info/METADATA
odoo14_addon_account_cash_invoice-14.0.1.3.0.dist-info/WHEEL
odoo14_addon_account_cash_invoice-14.0.1.3.0.dist-info/top_level.txt
odoo14_addon_account_cash_invoice-14.0.1.3.0.dist-info/RECORD
